vuabl/__init__.py
vuabl/__main__.py
vuabl/vuabl.py
vuabl/assets/dark.css
vuabl/assets/light.css
vuabl/data/__init__.py
vuabl/data/asset.py
vuabl/data/asset_data.py
vuabl/data/asset_type.py
vuabl/data/build_layout.py
vuabl/data/data_from_other_asset.py
vuabl/data/environment.py
vuabl/data/explicit_asset.py
vuabl/data/file.py
vuabl/data/group.py
vuabl/data/group_archive.py
vuabl/data/scope.py
vuabl/data/size_plot_data.py
vuabl/data/summary.py
vuabl/data/table_data.py
vuabl/layouts/__init__.py
vuabl/layouts/assets.py
vuabl/layouts/environment.py
vuabl/layouts/group.py
vuabl/layouts/summary.py
vuabl/parsing/__init__.py
vuabl/parsing/asset_type.py
vuabl/parsing/build_layout.py
vuabl/parsing/data_from_other_asset.py
vuabl/parsing/explicit_asset.py
vuabl/parsing/file.py
vuabl/parsing/group.py
vuabl/parsing/group_archive.py
vuabl/parsing/parameters.py
vuabl/parsing/summary.py
vuabl/plots/__init__.py
vuabl/plots/categories.py
vuabl/plots/groups.py
vuabl/tables/__init__.py
vuabl/tables/assets.py
vuabl/tables/group.py
vuabl/utils/__init__.py
vuabl/utils/arguments.py
vuabl/utils/conversion.py
vuabl/utils/layout_reader.py
vuabl/utils/theming.py
vuabl/utils/version.py
vuabl-1.1.0.dist-info/LICENSE
vuabl-1.1.0.dist-info/METADATA
vuabl-1.1.0.dist-info/WHEEL
vuabl-1.1.0.dist-info/entry_points.txt
vuabl-1.1.0.dist-info/top_level.txt
vuabl-1.1.0.dist-info/RECORD
