Metadata-Version: 2.1
Name: vuabl
Version: 1.1.0
Summary: Visualizer for Unity Addressables build layout
Home-page: https://github.com/CncealDVRflectN/vuabl
Author: Valery Zhuk
Author-email: zhuk.valeriy.98@gmail.com
License: MIT
Project-URL: Bug Tracker, https://github.com/CncealDVRflectN/vuabl/issues
Platform: UNKNOWN
Classifier: Programming Language :: Python :: 3.6
Classifier: License :: OSI Approved :: MIT License
Requires-Python: <4,>=3.6
License-File: LICENSE
Requires-Dist: dash (>=2.0.0)
Requires-Dist: dash-bootstrap-components (>=1.0.0b3)
Requires-Dist: pandas (>=1.3.0)
Requires-Dist: plotly (>=5.3.0)
